replx/__init__.py
replx/exceptions.py
replx/terminal.py
replx/agent/__init__.py
replx/agent/__main__.py
replx/agent/client.py
replx/agent/protocol.py
replx/agent/server.py
replx/cli/__init__.py
replx/cli/commands.py
replx/cli/helpers.py
replx/protocol/__init__.py
replx/protocol/base.py
replx/protocol/storage/__init__.py
replx/protocol/storage/base.py
replx/protocol/storage/serial.py
replx/protocol/storage/webrepl.py
replx/transport/__init__.py
replx/transport/base.py
replx/transport/serial.py
replx/transport/webrepl.py
replx-2.0.3.dist-info/licenses/LICENSE
replx-2.0.3.dist-info/METADATA
replx-2.0.3.dist-info/WHEEL
replx-2.0.3.dist-info/entry_points.txt
replx-2.0.3.dist-info/top_level.txt
replx-2.0.3.dist-info/RECORD
