Metadata-Version: 2.4
Name: replx
Version: 2.0.3
Summary: replx is a fast, modern MicroPython CLI: turbo REPL, robust file sync (put/get), project install, mpy-cross integration, and smart port discovery.
Author-email: "chanmin.park" <devcamp@gmail.com>
License: MIT License
Project-URL: Homepage, https://github.com/PlanXLab/replx
Project-URL: Repository, https://github.com/PlanXLab/replx
Project-URL: Issues, https://github.com/PlanXLab/replx/issues
Keywords: micropython,repl,serial,pyserial,typer,mpy-cross,deploy
Classifier: Environment :: Console
Classifier: Programming Language :: Python :: 3
Classifier: Programming Language :: Python :: 3 :: Only
Classifier: License :: OSI Approved :: MIT License
Classifier: Operating System :: OS Independent
Classifier: Topic :: Software Development :: Embedded Systems
Classifier: Topic :: System :: Hardware :: Universal Serial Bus (USB)
Requires-Python: >=3.10
License-File: LICENSE
Requires-Dist: typer>=0.12
Requires-Dist: rich>=13.0
Requires-Dist: pyserial>=3.5
Requires-Dist: mpy-cross>=1.26
Requires-Dist: websocket-client>=1.6.0
Dynamic: license-file
